Verilog Codes/sram.v
// Taha Izadi  Mohassel 402110543
`timescale 1ns/1ns

// asyncron sram module
module sram(
    input [8 :0] addr,
    inout [15:0] data,
    input        CE, OE, WE, UB, LB
);
    // internal memory array
    reg [15:0] memory [0:511];

    // READ
    assign #(15, 15, 4) data = (CE == 0 && WE == 1 && OE == 0) ?
                           {
                            (UB == 0 ? memory[addr][15:8] : 8'hzz), 
                            (LB == 0 ? memory[addr][7:0]  : 8'hzz)
                           } :
                           16'hzzzz;

    // WRITE
    always @(*)
    begin
        if (CE == 0 && WE == 0)
        begin
            if (LB == 0)
                memory[addr][7:0] <= #15 data[7:0];
            if (UB == 0)
                memory[addr][15:8] <= #15 data[15:8];
        end
    end
endmodule


module sram_tb;

    // sram signals
    reg  [8:0]  addr;
    reg         CE;
    reg         OE;
    reg         WE;
    reg         UB;
    reg         LB;
    
    // 2 way data pass
    wire [15:0] data;

    // loop counter
    integer count = 0;
    
    // variable for writing on data
    reg  [15:0] data_driver_reg;
    
    // writing on data based on WE signal
    assign data = (WE == 0) ? data_driver_reg : 16'hzzzz;

    // instance
    sram my_sram (
        .data(data),
        .addr(addr),
        .CE(CE),
        .OE(OE),
        .WE(WE),
        .UB(UB),
        .LB(LB)
    );

    // test block
    initial begin
        // vcd file handling
        $display("Initializing simulation...");
        $dumpfile("sram_simulation.vcd");
        $dumpvars(0, sram_tb);
        
        // initializing signals
        addr = 9'h0;
        CE = 1;
        OE = 1;
        WE = 1;
        UB = 1;
        LB = 1;
        data_driver_reg = 16'h0;
        
        #20; 

        // Phase 1: normal operation test
        $display("\nPHASE 1: Normal Operation Test (CE = 0)");

        // activating the chip
        CE = 0;
        
        // 1. writing address on lower byte for first 10
        $display("Step 1: Writing address to lower byte for addresses 0-9...");
        while(count < 10) begin
            addr = count;
            data_driver_reg = {8'h00, count[7:0]};
            $display("data is: %h", data_driver_reg);
            LB = 0;
            UB = 1;
            WE = 0;   
            #20;      
            WE = 1;   
            #5;       
            count = count + 1;
        end
        LB = 1; 
        #10;

        // 2. writing log2 of address on upper byte for second 10
        $display("Step 2: Writing $clog2(address) to upper byte for addresses 10-19...");
        while(count < 20) begin
            addr = count;
            data_driver_reg = {$clog2(count), 8'h00};
            LB = 1;
            UB = 0;
            WE = 0;   
            #20;
            WE = 1;   
            #5;
            count = count + 1;
        end
        UB = 1; 
        #10;
        
        // 3. writing randoms on third 10
        $display("Step 3: Writing random data to addresses 20-29...");
        while(count < 30) begin
            addr = count;
            data_driver_reg = $random;
            LB = 0;
            UB = 0;
            WE = 0;   
            #20;
            WE = 1;   
            #5;
            count = count + 1;
        end
        LB = 1;
        UB = 1;
        #10;
        
        // 4. reading first 30
        $display("Step 4: Reading and displaying data from addresses 0-29...");
        OE = 0;

        count = 0;
        while(count < 30) begin
            addr = count;

            // handling upper & lower
            if (count < 10) begin
                LB = 0;
                UB = 1;
            end
            if ((count > 9) && (count < 20)) begin
                LB = 1;
                UB = 0;
            end
            if (count > 19) begin
                LB = 0;
                UB = 0;
            end

            #20;
            $display("Read from addr[%0d]: data = %h", count, data);
            count = count + 1;
        end
        OE = 1;
        #20;
        
        // Phase 2: standby
        $display("\nPHASE 2: Standby Mode Test (CE = 1)");
        CE = 1;
        
        // 5. writing on standby mode
        $display("Step 5: Attempting to write to memory while in standby mode...");
        addr = 5;
        data_driver_reg = 16'hFFFF;
        WE = 0;
        LB = 0;
        UB = 0;
        #20;
        WE = 1;
        LB = 1;
        UB = 1;

        // 6. reading on standby mode
        $display("Step 6: Attempting to read from memory while in standby mode...");
        addr = 5;
        OE = 0;
        LB = 0;
        UB = 0;
        #20;
        $display("Attempted read from addr[5] while CE=1. Data bus is: %h", data);
        OE = 1;
        #10;

        // 7. checkkng the memory changes on standby mode
        // address: 5
        $display("Step 7: Verifying that memory content did NOT change...");
        CE = 0;
        OE = 0;
        addr = 5; 
        LB = 0;
        UB = 0;
        #20;
        $display("Read from addr[5] after standby test. Data is: %h (Should be xx05)", data);
        
        // address: 15
        addr = 15; 
        LB = 0;
        UB = 0;
        #20;
        $display("Read from addr[15] after standby test. Data is: %h (Should be 04xx)", data);
        OE = 1;

        // finish simulating
        #50;
        $display("\nSimulation finished.");
        $finish;
    end

endmodule

VCD Simulations/sram_simulation.vcd
$date
	Tue Jul 22 17:53:32 2025
$end
$version
	ModelSim Version 10.5b
$end
$timescale
	1ns
$end

$scope module sram_tb $end
$var reg 9 ! addr [8:0] $end
$var reg 1 " CE $end
$var reg 1 # OE $end
$var reg 1 $ WE $end
$var reg 1 % UB $end
$var reg 1 & LB $end
$var wire 1 ' data [15] $end
$var wire 1 ( data [14] $end
$var wire 1 ) data [13] $end
$var wire 1 * data [12] $end
$var wire 1 + data [11] $end
$var wire 1 , data [10] $end
$var wire 1 - data [9] $end
$var wire 1 . data [8] $end
$var wire 1 / data [7] $end
$var wire 1 0 data [6] $end
$var wire 1 1 data [5] $end
$var wire 1 2 data [4] $end
$var wire 1 3 data [3] $end
$var wire 1 4 data [2] $end
$var wire 1 5 data [1] $end
$var wire 1 6 data [0] $end
$var integer 32 7 count $end
$var reg 16 8 data_driver_reg [15:0] $end

$scope module my_sram $end
$var wire 1 9 addr [8] $end
$var wire 1 : addr [7] $end
$var wire 1 ; addr [6] $end
$var wire 1 < addr [5] $end
$var wire 1 = addr [4] $end
$var wire 1 > addr [3] $end
$var wire 1 ? addr [2] $end
$var wire 1 @ addr [1] $end
$var wire 1 A addr [0] $end
$var wire 1 ' data [15] $end
$var wire 1 ( data [14] $end
$var wire 1 ) data [13] $end
$var wire 1 * data [12] $end
$var wire 1 + data [11] $end
$var wire 1 , data [10] $end
$var wire 1 - data [9] $end
$var wire 1 . data [8] $end
$var wire 1 / data [7] $end
$var wire 1 0 data [6] $end
$var wire 1 1 data [5] $end
$var wire 1 2 data [4] $end
$var wire 1 3 data [3] $end
$var wire 1 4 data [2] $end
$var wire 1 5 data [1] $end
$var wire 1 6 data [0] $end
$var wire 1 B CE $end
$var wire 1 C OE $end
$var wire 1 D WE $end
$var wire 1 E UB $end
$var wire 1 F LB $end
$upscope $end
$upscope $end
$enddefinitions $end
#0
$dumpvars
b0 !
1"
1#
1$
1%
1&
b0 8
b0 7
x6
x5
x4
x3
x2
x1
x0
x/
x.
x-
x,
x+
x*
x)
x(
x'
1F
1E
1D
1C
1B
0A
0@
0?
0>
0=
0<
0;
0:
09
$end
#4
z'
z(
z)
z*
z+
z,
z-
z.
z/
z0
z1
z2
z3
z4
z5
z6
#20
0"
0&
0$
0B
0F
06
05
04
03
02
01
00
0/
0.
0-
0,
0+
0*
0)
0(
0'
0D
#40
1$
z6
z5
z4
z3
z2
z1
z0
z/
z.
z-
z,
z+
z*
z)
z(
z'
1D
#45
b1 7
b1 !
b1 8
0$
16
05
04
03
02
01
00
0/
0.
0-
0,
0+
0*
0)
0(
0'
1A
0D
#65
1$
z6
z5
z4
z3
z2
z1
z0
z/
z.
z-
z,
z+
z*
z)
z(
z'
1D
#70
b10 7
b10 !
b10 8
0$
06
15
04
03
02
01
00
0/
0.
0-
0,
0+
0*
0)
0(
0'
0A
1@
0D
#90
1$
z6
z5
z4
z3
z2
z1
z0
z/
z.
z-
z,
z+
z*
z)
z(
z'
1D
#95
b11 7
b11 !
b11 8
0$
16
15
04
03
02
01
00
0/
0.
0-
0,
0+
0*
0)
0(
0'
1A
0D
#115
1$
z6
z5
z4
z3
z2
z1
z0
z/
z.
z-
z,
z+
z*
z)
z(
z'
1D
#120
b100 7
b100 !
b100 8
0$
06
05
14
03
02
01
00
0/
0.
0-
0,
0+
0*
0)
0(
0'
0A
0@
1?
0D
#140
1$
z6
z5
z4
z3
z2
z1
z0
z/
z.
z-
z,
z+
z*
z)
z(
z'
1D
#145
b101 7
b101 !
b101 8
0$
16
05
14
03
02
01
00
0/
0.
0-
0,
0+
0*
0)
0(
0'
1A
0D
#165
1$
z6
z5
z4
z3
z2
z1
z0
z/
z.
z-
z,
z+
z*
z)
z(
z'
1D
#170
b110 7
b110 !
b110 8
0$
06
15
14
03
02
01
00
0/
0.
0-
0,
0+
0*
0)
0(
0'
0A
1@
0D
#190
1$
z6
z5
z4
z3
z2
z1
z0
z/
z.
z-
z,
z+
z*
z)
z(
z'
1D
#195
b111 7
b111 !
b111 8
0$
16
15
14
03
02
01
00
0/
0.
0-
0,
0+
0*
0)
0(
0'
1A
0D
#215
1$
z6
z5
z4
z3
z2
z1
z0
z/
z.
z-
z,
z+
z*
z)
z(
z'
1D
#220
b1000 7
b1000 !
b1000 8
0$
06
05
04
13
02
01
00
0/
0.
0-
0,
0+
0*
0)
0(
0'
0A
0@
0?
1>
0D
#240
1$
z6
z5
z4
z3
z2
z1
z0
z/
z.
z-
z,
z+
z*
z)
z(
z'
1D
#245
b1001 7
b1001 !
b1001 8
0$
16
05
04
13
02
01
00
0/
0.
0-
0,
0+
0*
0)
0(
0'
1A
0D
#265
1$
z6
z5
z4
z3
z2
z1
z0
z/
z.
z-
z,
z+
z*
z)
z(
z'
1D
#270
b1010 7
1&
1F
#280
b1010 !
b10000000000 8
0%
0$
06
05
04
03
02
01
00
0/
0.
0-
1,
0+
0*
0)
0(
0'
0A
1@
0E
0D
#300
1$
z6
z5
z4
z3
z2
z1
z0
z/
z.
z-
z,
z+
z*
z)
z(
z'
1D
#305
b1011 7
b1011 !
0$
06
05
04
03
02
01
00
0/
0.
0-
1,
0+
0*
0)
0(
0'
1A
0D
#325
1$
z6
z5
z4
z3
z2
z1
z0
z/
z.
z-
z,
z+
z*
z)
z(
z'
1D
#330
b1100 7
b1100 !
0$
06
05
04
03
02
01
00
0/
0.
0-
1,
0+
0*
0)
0(
0'
0A
0@
1?
0D
#350
1$
z6
z5
z4
z3
z2
z1
z0
z/
z.
z-
z,
z+
z*
z)
z(
z'
1D
#355
b1101 7
b1101 !
0$
06
05
04
03
02
01
00
0/
0.
0-
1,
0+
0*
0)
0(
0'
1A
0D
#375
1$
z6
z5
z4
z3
z2
z1
z0
z/
z.
z-
z,
z+
z*
z)
z(
z'
1D
#380
b1110 7
b1110 !
0$
06
05
04
03
02
01
00
0/
0.
0-
1,
0+
0*
0)
0(
0'
0A
1@
0D
#400
1$
z6
z5
z4
z3
z2
z1
z0
z/
z.
z-
z,
z+
z*
z)
z(
z'
1D
#405
b1111 7
b1111 !
0$
06
05
04
03
02
01
00
0/
0.
0-
1,
0+
0*
0)
0(
0'
1A
0D
#425
1$
z6
z5
z4
z3
z2
z1
z0
z/
z.
z-
z,
z+
z*
z)
z(
z'
1D
#430
b10000 7
b10000 !
0$
06
05
04
03
02
01
00
0/
0.
0-
1,
0+
0*
0)
0(
0'
0A
0@
0?
0>
1=
0D
#450
1$
z6
z5
z4
z3
z2
z1
z0
z/
z.
z-
z,
z+
z*
z)
z(
z'
1D
#455
b10001 7
b10001 !
b10100000000 8
0$
06
05
04
03
02
01
00
0/
1.
0-
1,
0+
0*
0)
0(
0'
1A
0D
#475
1$
z6
z5
z4
z3
z2
z1
z0
z/
z.
z-
z,
z+
z*
z)
z(
z'
1D
#480
b10010 7
b10010 !
0$
06
05
04
03
02
01
00
0/
1.
0-
1,
0+
0*
0)
0(
0'
0A
1@
0D
#500
1$
z6
z5
z4
z3
z2
z1
z0
z/
z.
z-
z,
z+
z*
z)
z(
z'
1D
#505
b10011 7
b10011 !
0$
06
05
04
03
02
01
00
0/
1.
0-
1,
0+
0*
0)
0(
0'
1A
0D
#525
1$
z6
z5
z4
z3
z2
z1
z0
z/
z.
z-
z,
z+
z*
z)
z(
z'
1D
#530
b10100 7
1%
1E
#540
b10100 !
b11010100100100 8
0&
0%
0$
06
05
14
03
02
11
00
0/
1.
0-
1,
0+
1*
1)
0(
0'
0A
0@
1?
0F
0E
0D
#560
1$
z6
z5
z4
z3
z2
z1
z0
z/
z.
z-
z,
z+
z*
z)
z(
z'
1D
#565
b10101 7
b10101 !
b101111010000001 8
0$
16
05
04
03
02
01
00
1/
0.
1-
1,
1+
1*
0)
1(
0'
1A
0D
#585
1$
z6
z5
z4
z3
z2
z1
z0
z/
z.
z-
z,
z+
z*
z)
z(
z'
1D
#590
b10110 7
b10110 !
b1101011000001001 8
0$
16
05
04
13
02
01
00
0/
0.
1-
1,
0+
1*
0)
1(
1'
0A
1@
0D
#610
1$
z6
z5
z4
z3
z2
z1
z0
z/
z.
z-
z,
z+
z*
z)
z(
z'
1D
#615
b10111 7
b10111 !
b101011001100011 8
0$
16
15
04
03
02
11
10
0/
0.
1-
1,
0+
1*
0)
1(
0'
1A
0D
#635
1$
z6
z5
z4
z3
z2
z1
z0
z/
z.
z-
z,
z+
z*
z)
z(
z'
1D
#640
b11000 7
b11000 !
b111101100001101 8
0$
16
05
14
13
02
01
00
0/
1.
1-
0,
1+
1*
1)
1(
0'
0A
0@
0?
1>
0D
#660
1$
z6
z5
z4
z3
z2
z1
z0
z/
z.
z-
z,
z+
z*
z)
z(
z'
1D
#665
b11001 7
b11001 !
b1001100110001101 8
0$
16
05
14
13
02
01
00
1/
1.
0-
0,
1+
1*
0)
0(
1'
1A
0D
#685
1$
z6
z5
z4
z3
z2
z1
z0
z/
z.
z-
z,
z+
z*
z)
z(
z'
1D
#690
b11010 7
b11010 !
b1000010001100101 8
0$
16
05
14
03
02
11
10
0/
0.
0-
1,
0+
0*
0)
0(
1'
0A
1@
0D
#710
1$
z6
z5
z4
z3
z2
z1
z0
z/
z.
z-
z,
z+
z*
z)
z(
z'
1D
#715
b11011 7
b11011 !
b101001000010010 8
0$
06
15
04
03
12
01
00
0/
0.
1-
0,
0+
1*
0)
1(
0'
1A
0D
#735
1$
z6
z5
z4
z3
z2
z1
z0
z/
z.
z-
z,
z+
z*
z)
z(
z'
1D
#740
b11100 7
b11100 !
b1110001100000001 8
0$
16
05
04
03
02
01
00
0/
1.
1-
0,
0+
0*
1)
1(
1'
0A
0@
1?
0D
#760
1$
z6
z5
z4
z3
z2
z1
z0
z/
z.
z-
z,
z+
z*
z)
z(
z'
1D
#765
b11101 7
b11101 !
b1100110100001101 8
0$
16
05
14
13
02
01
00
0/
1.
0-
1,
1+
0*
0)
1(
1'
1A
0D
#785
1$
z6
z5
z4
z3
z2
z1
z0
z/
z.
z-
z,
z+
z*
z)
z(
z'
1D
#790
b11110 7
1&
1%
1F
1E
#800
0#
b0 7
b0 !
0&
0C
0A
0?
0>
0=
0F
#815
0/
00
01
02
03
04
05
06
#820
b1 7
b1 !
1A
#835
16
#840
b10 7
b10 !
0A
1@
#855
15
06
#860
b11 7
b11 !
1A
#875
16
#880
b100 7
b100 !
0A
0@
1?
#895
14
05
06
#900
b101 7
b101 !
1A
#915
16
#920
b110 7
b110 !
0A
1@
#935
15
06
#940
b111 7
b111 !
1A
#955
16
#960
b1000 7
b1000 !
0A
0@
0?
1>
#975
13
04
05
06
#980
b1001 7
b1001 !
1A
#995
16
#1000
b1010 7
b1010 !
1&
0%
0A
1@
1F
0E
#1004
0'
0(
0)
0*
0+
1,
0-
0.
z/
z0
z1
z2
z3
z4
z5
z6
#1020
b1011 7
b1011 !
1A
#1040
b1100 7
b1100 !
0A
0@
1?
#1060
b1101 7
b1101 !
1A
#1080
b1110 7
b1110 !
0A
1@
#1100
b1111 7
b1111 !
1A
#1120
b10000 7
b10000 !
0A
0@
0?
0>
1=
#1140
b10001 7
b10001 !
1A
#1144
1.
#1160
b10010 7
b10010 !
0A
1@
#1180
b10011 7
b10011 !
1A
#1200
b10100 7
b10100 !
0&
0A
0@
1?
0F
#1215
1)
1*
0/
00
11
02
03
14
05
06
#1220
b10101 7
b10101 !
1A
#1235
1(
0)
1+
1-
0.
1/
01
04
16
#1240
b10110 7
b10110 !
0A
1@
#1255
1'
0+
0/
13
#1260
b10111 7
b10111 !
1A
#1275
0'
10
11
03
15
#1280
b11000 7
b11000 !
0A
0@
0?
1>
#1295
1)
1+
0,
1.
00
01
13
14
05
#1300
b11001 7
b11001 !
1A
#1315
1'
0(
0)
0-
1/
#1320
b11010 7
b11010 !
0A
1@
#1335
0*
0+
1,
0.
0/
10
11
03
#1340
b11011 7
b11011 !
1A
#1355
0'
1(
1*
0,
1-
00
01
12
04
15
06
#1360
b11100 7
b11100 !
0A
0@
1?
#1375
1'
1)
0*
1.
02
05
16
#1380
b11101 7
b11101 !
1A
#1395
0)
1+
1,
0-
13
14
#1400
b11110 7
1#
1C
#1404
z'
z(
z)
z*
z+
z,
z-
z.
z/
z0
z1
z2
z3
z4
z5
z6
#1420
1"
b101 !
b1111111111111111 8
0$
1B
16
15
14
13
12
11
10
1/
1.
1-
1,
1+
1*
1)
1(
1'
0>
0=
0D
#1440
1$
1&
1%
0#
0&
0%
0C
z6
z5
z4
z3
z2
z1
z0
z/
z.
z-
z,
z+
z*
z)
z(
z'
1D
#1460
1#
1C
#1470
0"
0#
0C
0B
#1485
x'
x(
x)
x*
x+
x,
x-
x.
0/
00
01
02
03
14
05
16
#1490
b1111 !
1@
1>
#1494
0'
0(
0)
0*
0+
1,
0-
0.
x/
x0
x1
x2
x3
x4
x5
x6
#1510
1#
1C
#1514
z'
z(
z)
z*
z+
z,
z-
z.
z/
z0
z1
z2
z3
z4
z5
z6
